{
  "type": "morning_paper",
  "date": "2026-07-11",
  "weather": {
    "now_f": 73,
    "hi_f": 75,
    "lo_f": 56,
    "precip_pct": 3,
    "desc": "overcast"
  },
  "story_count": 60,
  "score_count": 2,
  "top": [
    {
      "section": "World",
      "title": "Palestinian aid worker who organized World Cup screenings killed in Israeli strike",
      "source": "npr.org"
    },
    {
      "section": "U.S. National",
      "title": "Trump\u2019s Posts on Singing Somali Schoolchildren Stir Anger in Minnesota",
      "source": "nytimes.com"
    },
    {
      "section": "Pacific Northwest",
      "title": "World Cup soccer star dead at 25 days after playing in tournament: \u2018A gifted player\u2019",
      "source": "oregonlive.com"
    },
    {
      "section": "Science & Environment",
      "title": "Fastest spider in the world? This huge, hairy-legged Australian arachnid may be the quickest on the planet",
      "source": "theguardian.com"
    },
    {
      "section": "Tech & Business",
      "title": "After years of teasing, the viral Nopia synth is \u2018basically finished\u2019",
      "source": "theverge.com"
    },
    {
      "section": "The Lighter Side",
      "title": "\u2018Game-Changing\u2019 Saliva Test Can Diagnose Endometriosis in Days Rather Than Years",
      "source": "goodnewsnetwork.org"
    }
  ]
}