{
  "type": "morning_paper",
  "date": "2026-07-16",
  "weather": {
    "name": "Port Orchard",
    "now_f": 61,
    "hi_f": 70,
    "lo_f": 58,
    "precip_pct": 37,
    "desc": "light rain"
  },
  "weather_all": [
    {
      "name": "Port Orchard",
      "now_f": 61,
      "hi_f": 70,
      "lo_f": 58,
      "precip_pct": 37,
      "desc": "light rain"
    },
    {
      "name": "Lebanon, OR",
      "now_f": 59,
      "hi_f": 73,
      "lo_f": 55,
      "precip_pct": 20,
      "desc": "overcast"
    }
  ],
  "story_count": 71,
  "score_count": 1,
  "top": [
    {
      "section": "U.S. National",
      "title": "Here\u2019s the latest.",
      "source": "nytimes.com"
    },
    {
      "section": "World",
      "title": "World Cup: Why is there a third-place playoff between France and England?",
      "source": "aljazeera.com"
    },
    {
      "section": "Pacific Northwest",
      "title": "US expands strikes into northern Iran and disables ship trying to run blockade",
      "source": "opb.org"
    },
    {
      "section": "Tech & Business",
      "title": "Truth Social launches service to give Wall Street traders an edge with real-time service",
      "source": "cnbc.com"
    },
    {
      "section": "Science & Environment",
      "title": "Private schools offer 41% more tree shade than state schools in England",
      "source": "theguardian.com"
    },
    {
      "section": "The Lighter Side",
      "title": "4 Forgotten Frontier Towns Most People Have Never Heard Of",
      "source": "mentalfloss.com"
    }
  ]
}